[
        {
          "name": "La Ferme Des Marettes",
          "theme": "Nature & plein air",
          "themeDetail": "Ferme & animaux",
          "distanceKm": 6.1,
          "durationMin": 12,
          "googleMapsUrl": "https://www.google.com/maps/dir/2api=1&origin=45.366633,4901511",
          "routeUrl": "https://maps.app.goo.gl/vsipe5cYjQHKZamWi",
          "lat": 45.330745,
          "lng": 4.843112
        },
        {
          "name": "Musée des Mariniers",
          "theme": "Patrimoine & culture",
          "themeDetail": "Patrimoine & musées",
          "distanceKm": 7.4,
          "durationMin": 14,
          "googleMapsUrl": "https://www.google.com/maps/dir/?api=1&origin=45.366833.4.901511&destination=45",
          "routeUrl": "https://maps.app.goo.gl/omgkV5A6qYD1wXK5",
          "lat": 45.3403789,
          "lng": 4.8143184
        },
        {
          "name": "Bar les Galets/La cerisaie",
          "theme": "Restaurants",
          "themeDetail": "Restaurants",
          "distanceKm": 7.5,
          "durationMin": 34,
          "googleMapsUrl": "https://www.google.com/maps/dir/Zapis1&gcutio-45",
          "routeUrl": "https://maps.app.goo.gl/KAWF039KGH6gai(2",
          "lat": 45.33883,
          "lng": 4.81379
        },
        {
          "name": "Games Factory Salaise",
          "theme": "Aventure & loisirs",
          "themeDetail": "Loisirs Indoor",
          "distanceKm": 7.5,
          "durationMin": 14,
          "googleMapsUrl": "maps.app.goo.gl/MMOTdpCmtm@130nw6",
          "routeUrl": "https://www.google.com/maps/dir/?api=1&origin=45.366833.4901511&destination",
          "lat": 45.338374,
          "lng": 4.814779
        },
        {
          "name": "Nej Et Restaurant",
          "theme": "Restaurants",
          "themeDetail": "Restaurants",
          "distanceKm": 7.6,
          "durationMin": 14,
          "googleMapsUrl": "https://www.google.com/maps/dir/?api=1&origin=45.366833.4.901511&destination=45",
          "routeUrl": "https://maps.app.goo.gl/nMZbK2d1YdRsao/19",
          "lat": 45.33829,
          "lng": 4.81401
        },
        {
          "name": "Laser Stadium Trampoline Park",
          "theme": "Aventure & loisirs",
          "themeDetail": "Loisirs indoor",
          "distanceKm": 7.7,
          "durationMin": 14,
          "googleMapsUrl": "https://maps.app.goo.gl/AiAFZ6166KOXHNWS",
          "routeUrl": "https://www.google.com/maps/dir/?ant=1&origin=45.368833.4.901511&destination=45.336589.4.812755&tayeimode=dhving",
          "lat": null,
          "lng": null
        },
        {
          "name": "Restaurant A 4 Mains",
          "theme": "Restaurants",
          "themeDetail": "Restaurants",
          "distanceKm": 7.8,
          "durationMin": 14,
          "googleMapsUrl": "https://www.google.com/maps/dir/?api=1&origin=45.3668334.901511&destination",
          "routeUrl": "https://maps.app.goo.gl/cfalim1PxdCJx46",
          "lat": 45.34215,
          "lng": 4.80837
        },
        {
          "name": "Dar Benziane",
          "theme": "Restaurants",
          "themeDetail": "Restaurants",
          "distanceKm": 7.9,
          "durationMin": 14,
          "googleMapsUrl": "https://www.google.com/maps/dir/?uttis1&origin=45",
          "routeUrl": "https://maps.app.goo.gl/OECZCIAFORETHK0am7",
          "lat": 45.37127,
          "lng": 4.80142
        },
        {
          "name": "Kimudjuk",
          "theme": "Aventure & loisirs",
          "themeDetail": "Loisirs indoor",
          "distanceKm": 8.3,
          "durationMin": 15,
          "googleMapsUrl": "https://www.google.com/maps/dir/Zapi=1&gijn-45-366633,4.901511&destination=45",
          "routeUrl": "https://maps.app.goo.gl/b01bgusanoSK5hzo",
          "lat": 45.359474,
          "lng": 4.795653
        },
        {
          "name": "Tac'Aventures",
          "theme": "Aventure & loisirs",
          "themeDetail": "Aventure & grimpe",
          "distanceKm": 4,
          "durationMin": 15,
          "googleMapsUrl": "https://www.google.com/maps/dir/?m=1&primm-45.366833.4.901511&destination-45.401514,4",
          "routeUrl": "https://maps.app.goo.gl/vMARGYTSto",
          "lat": null,
          "lng": null
        },
        {
          "name": "Parc Oasis Aventura (activité physique)",
          "theme": "Aventure & loisirs",
          "themeDetail": "Aventure & grimpe",
          "distanceKm": 8.6,
          "durationMin": 15,
          "googleMapsUrl": "https://www.google.com/maps/dir/?utis1&origin=45.366833.4.901511&destination=45",
          "routeUrl": "https://maps.app.goo.gl/owenTHUXFT2R76GT8",
          "lat": 45.3100271,
          "lng": 4.8276362
        },
        {
          "name": "Les Jardins de Brogieux",
          "theme": "Nature & plein air",
          "themeDetail": "Nature & jardins",
          "distanceKm": 8.9,
          "durationMin": 16,
          "googleMapsUrl": "https://maps.app.goo.gl/sGZDUNKurjp_thg",
          "routeUrl": "https://www.google.com/maps/dir/Papi=1&origin=45.366833.4.901511",
          "lat": 45.390306,
          "lng": 4.792779
        },
        {
          "name": "Parc de Loisirs Mad Maze",
          "theme": "Aventure & loisirs",
          "themeDetail": "Aventure & jeux",
          "distanceKm": 12.3,
          "durationMin": 20,
          "googleMapsUrl": "https://maps.app.goo.gl/tHokteuingTeng505",
          "routeUrl": "https://wwwgoogle.com/maps/dir/?ant=1&aneio=45",
          "lat": 45.41508,
          "lng": 4.759537
        },
        {
          "name": "Château-Grillet AOC",
          "theme": "Terroir & gastronomie",
          "themeDetail": "Vin & terroir",
          "distanceKm": 13.1,
          "durationMin": 21,
          "googleMapsUrl": "https://www.google.com/maps/dir//agi-180nm",
          "routeUrl": "https://maps.app.goo.gl/6LUWknGFPhADhy",
          "lat": 45.4675379,
          "lng": 4.814918
        },
        {
          "name": "Jungle parc",
          "theme": "Aventure & loisirs",
          "themeDetail": "Aventure & grimpe",
          "distanceKm": 13.9,
          "durationMin": 22,
          "googleMapsUrl": "https://www.google.com/maps/dir/?agi-18ongan-45-3608334901511&mation-45",
          "routeUrl": "https://maps.app.goo.gl/",
          "lat": 45.18735,
          "lng": 4.7715409
        },
        {
          "name": "Wise and Ride Condrieu visite des caves à vélo",
          "theme": "Terroir & gastronomie",
          "themeDetail": "Vin & terroir",
          "distanceKm": 15.4,
          "durationMin": 19,
          "googleMapsUrl": "https://www.google.com/maps/dir/?api=1&origin=45.366833.4.901511&destination=45.4688028.4.7681064&travelmóde",
          "routeUrl": "https://maps.app.goo.gl/wCEUKBONEJMIZRCD9",
          "lat": null,
          "lng": null
        },
        {
          "name": "Villa Garden",
          "theme": "Aventure & loisirs",
          "themeDetail": "Loisirs & parc",
          "distanceKm": 16.1,
          "durationMin": 20,
          "googleMapsUrl": "https://wowww.google.com/maps/dir/2api=1&origin=45.366633.4.901511&destination",
          "routeUrl": "https://maps.app.goo.gl/x5vtXcWlXmllyQYjz5",
          "lat": 45.510494,
          "lng": 4.872295
        },
        {
          "name": "Saut de Lorette (site historique)",
          "theme": "Patrimoine & culture",
          "themeDetail": "Patrimoine & musées",
          "distanceKm": 17.5,
          "durationMin": 21,
          "googleMapsUrl": "https://www.google.com/maps/dir/?api=1",
          "routeUrl": "https://maps.app.goo.gl/czrhZeacCvMUL7w36",
          "lat": 45.340646,
          "lng": 4.681061
        },
        {
          "name": "LA GRANDE EVASION Escape Game Vienne",
          "theme": "Escape Games",
          "themeDetail": "Escape game",
          "distanceKm": 17.6,
          "durationMin": 21,
          "googleMapsUrl": "https://maps.app.goo.gl/ayuub",
          "routeUrl": "https://maps.app.goo.gl/p7LPLW4CM5Tpw57F6",
          "lat": null,
          "lng": null
        },
        {
          "name": "Indian Street Food",
          "theme": "Restaurants",
          "themeDetail": "Restaurants",
          "distanceKm": 17.9,
          "durationMin": 22,
          "googleMapsUrl": "https://www.google.com/maps/dir/?api=1&origin=45",
          "routeUrl": "https://www.google.com/maps/dir/?api=1&orijin-45",
          "lat": 45.5235639,
          "lng": 4.873337
        },
        {
          "name": "Alquimia",
          "theme": "Restaurants",
          "themeDetail": "Restaurants",
          "distanceKm": 17.9,
          "durationMin": 22,
          "googleMapsUrl": "https://maps.app.goo.gl/Bwi4pRrN10RHKAEZZ",
          "routeUrl": "https://www.google.com/maps/dir//agi=180nm0-45.366833.4.901511&destination-45",
          "lat": 45.52609,
          "lng": 4.87144
        },
        {
          "name": "Mama Trattoria",
          "theme": "Restaurants",
          "themeDetail": "Restaurants",
          "distanceKm": 17.9,
          "durationMin": 22,
          "googleMapsUrl": "https://www.google.com/maps/dir/?apie",
          "routeUrl": "https://maps.app.goo.gl/QRAZBOJ3ZEHPLEAt",
          "lat": 45.52678,
          "lng": 4.87292
        },
        {
          "name": "Restaurant Les Frangins",
          "theme": "Restaurants",
          "themeDetail": "Restaurants",
          "distanceKm": 17.9,
          "durationMin": 22,
          "googleMapsUrl": "https://maps.app.goo.gl/5TRYGHFvkwaved",
          "routeUrl": "https://www.google.com/maps/dir/?api=1&origin=45.366833.4.901511&destination=45.52645.4",
          "lat": null,
          "lng": 4.87312
        },
        {
          "name": "Restaurant Caprice Kebab Vienne",
          "theme": "Restaurants",
          "themeDetail": "Restaurants",
          "distanceKm": 17.9,
          "durationMin": 22,
          "googleMapsUrl": "https://www.google.com/maps/dir/?api=1&orimo=45.366833,4.901511&destination=45.52699,4.87281&travelmode",
          "routeUrl": "https://maps.app.goo.gl/09%(C2kSzsnytos",
          "lat": null,
          "lng": null
        },
        {
          "name": "Archeological Gardens of Cybele, Vienne",
          "theme": "Patrimoine & culture",
          "themeDetail": "Patrimoine & musées",
          "distanceKm": 17.9,
          "durationMin": 22,
          "googleMapsUrl": "https://www.google.com/maps/dir/?api=1&origin=45.366633.4901511&destination:45",
          "routeUrl": "https://maps.app.goo.gl/mild71359ZM260859",
          "lat": 45.5270996,
          "lng": 4.8735728
        },
        {
          "name": "Musée du Parchemin",
          "theme": "Patrimoine & culture",
          "themeDetail": "Patrimoine & musées",
          "distanceKm": 17.9,
          "durationMin": 22,
          "googleMapsUrl": "https://www.google.com/maps/dir/?uttis1&origin=45-366633.4.901511&destination=45",
          "routeUrl": "https://maps.app.goo.gl/AuNcW2KVTbYmWRUHS",
          "lat": 45.526574,
          "lng": 4.8230526
        },
        {
          "name": "Museum of Fine Arts and Archeology of Vienne",
          "theme": "Patrimoine & culture",
          "themeDetail": "Patrimoine & musées",
          "distanceKm": 17.9,
          "durationMin": 22,
          "googleMapsUrl": "https://www.google.com/maps/dir/",
          "routeUrl": "https://maps.app.goo.gl/GsBmH56QEFpLU20659",
          "lat": 45.5268287,
          "lng": 4.873046
        },
        {
          "name": "Restaurant Vienne 38: Chichi Pizza",
          "theme": "Restaurants",
          "themeDetail": "Restaurants",
          "distanceKm": 18,
          "durationMin": 22,
          "googleMapsUrl": "https://maps.app.goo.gl/SbKIWIVUKRSTINZ",
          "routeUrl": "https://www.google.com/maps/dir/?api=1&quen-45.3668.33,4.901511&destination",
          "lat": 45.52712,
          "lng": 4.87258
        },
        {
          "name": "WAM PARK Lyon-Condrieu",
          "theme": "Terroir & gastronomie",
          "themeDetail": "Aventure & aquatique",
          "distanceKm": 18.1,
          "durationMin": 22,
          "googleMapsUrl": "https://www.google.com/maps/dir/?api=1&origin=45.366833,4901511&destination-45-492006,4.753052&trowelmode-driving",
          "routeUrl": "https://maps.app.goo.gl/rasrinn9YThe79QH7",
          "lat": null,
          "lng": null
        },
        {
          "name": "Alt'fil parcabout",
          "theme": "Aventure & loisirs",
          "themeDetail": "Aventure & grimpe",
          "distanceKm": 18.4,
          "durationMin": 22,
          "googleMapsUrl": "https://www.google.com/maps/dir/",
          "routeUrl": "https://maps.app.goo.gl/N233bCeUKbarnwHd6",
          "lat": 45.284783,
          "lng": 4.698008
        },
        {
          "name": "Musée et sites archéologiques de Saint-Romain-en-Gal",
          "theme": "Patrimoine & culture",
          "themeDetail": "Patrimoine & musées",
          "distanceKm": 18.6,
          "durationMin": 22,
          "googleMapsUrl": "https://www.google.com/maps/dir/?api=1&origin=45.366833.4.901511",
          "routeUrl": "https://maps.app.goo.gl/LyNT2P4edixbu1116",
          "lat": 45.5325438,
          "lng": 4.886452
        },
        {
          "name": "Le Tremplin (randonnée)",
          "theme": "Nature & plein air",
          "themeDetail": "Randonnée & nature",
          "distanceKm": 20.7,
          "durationMin": 24,
          "googleMapsUrl": "http://google.com/maps/dir/",
          "routeUrl": "https://maps.app.goo.gl/zAgBywieuNFUyacz",
          "lat": 45.259237,
          "lng": 4.685845
        },
        {
          "name": "Cimes Aventures Septème 38780",
          "theme": "Aventure & loisirs",
          "themeDetail": "Aventure & grimpe",
          "distanceKm": 20.8,
          "durationMin": 24,
          "googleMapsUrl": "https://www.google.com/maps/dir/?api=1&00m0=45.366833.4.901511&destination-45",
          "routeUrl": "https://maps.app.goo.gl/e7ZingXr308",
          "lat": 45.5499722,
          "lng": 4.8565776
        },
        {
          "name": "Zig Zag 07 / Lamas Des Plaines",
          "theme": "Aventure & loisirs",
          "themeDetail": "Aventure & jeux / Ferme",
          "distanceKm": 22.5,
          "durationMin": 26,
          "googleMapsUrl": "https://www.google.com/maps/dir/?api=1&origin=45.3668.33.4.901511&destmation-05",
          "routeUrl": "https://maps.app.goo.gl/oj42gAY2hXSVEJA",
          "lat": 45.246758,
          "lng": 4.671124
        },
        {
          "name": "La Mourine Maison des Forgerons",
          "theme": "Patrimoine & culture",
          "themeDetail": "Patrimoine & musées",
          "distanceKm": 22.7,
          "durationMin": 26,
          "googleMapsUrl": "https://maps.app.goo.gl/aSHNIG_OellenDIVIZ",
          "routeUrl": "https://www.google.com/maps/dir/?ani=1&origin=45.366833.4.901511&destination=45",
          "lat": 45.3238684,
          "lng": 4.6185938
        },
        {
          "name": "100 Issues-Annonay Escape Game",
          "theme": "Escape Games",
          "themeDetail": "Escape game",
          "distanceKm": 23,
          "durationMin": 26,
          "googleMapsUrl": "https://www.google.com/maps/dir/2api=1&gcipin-45",
          "routeUrl": "https://maps.app.goo.gl/tkJgYZFb4xQhCUNOG",
          "lat": 45.238147,
          "lng": 4.671109
        },
        {
          "name": "No escape/Le Space game",
          "theme": "Escape Games",
          "themeDetail": "Escape game",
          "distanceKm": 23,
          "durationMin": 26,
          "googleMapsUrl": "https://wowww.google.com/maps/dir/?m=1&origin=45.366833.4.901511&destination-45",
          "routeUrl": "https://www.google.com/maps/dir/?utti=1&origin=45.366833.4.901511&destination=45234814.4.671277&travelmode",
          "lat": 45.238106,
          "lng": 4.671229
        },
        {
          "name": "Centre Aquatique Aquavaure-Annonay",
          "theme": "Terroir & gastronomie",
          "themeDetail": "Piscine & aquatique",
          "distanceKm": 23.3,
          "durationMin": 26,
          "googleMapsUrl": "https://maps.app.goo.gl/6VHA4Bsmy4VM5B58",
          "routeUrl": null,
          "lat": null,
          "lng": null
        },
        {
          "name": "Aqueduc du Gorneton",
          "theme": "Patrimoine & culture",
          "themeDetail": "Patrimoine & sites",
          "distanceKm": 24.5,
          "durationMin": 28,
          "googleMapsUrl": "https://maps.app.goo.gl/kfanTW2536kkVkY7",
          "routeUrl": "https://www.google.com/maps/dir/?api=1&origin=45.366833,4.901511&destination=45",
          "lat": 45.5853406,
          "lng": 4.8625687
        },
        {
          "name": "Maison des Tresses et Lacets",
          "theme": "Patrimoine & culture",
          "themeDetail": "Patrimoine & musées",
          "distanceKm": 24.6,
          "durationMin": 28,
          "googleMapsUrl": "https://maps.app.goo.gl/cRpXrMi4eV5v166",
          "routeUrl": "https://www.google.com/maps/dir/Pant=1&origin=45.366833.4.901511&destination=45",
          "lat": 45.286259,
          "lng": 4.609635
        },
    {
      "name": "Le Petit Glacier Restaurant-Bar-Tabac-Petite épicerie",
      "theme": "Restaurants",
      "themeDetail": "Restaurants",
      "distanceKm": 1,
      "durationMin": 7,
      "googleMapsUrl": "https://maps.app.goo.gl/Jm2EBXzMLKpM6CW6A",
      "routeUrl": "https://www.google.com/maps/dir/?api=1&origin=45.366833,4.901511&destination=45.35791,4.90259&travelmode=driving",
      "lat": 45.35791,
      "lng": 4.90259
    },
    {
      "name": "Tour D'Anjou",
      "theme": "Nature & plein air",
      "themeDetail": "Point de vue & balade",
      "distanceKm": 1,
      "durationMin": 7,
      "googleMapsUrl": "https://maps.app.goo.gl/FyCL3LMYFs2HAM9C8",
      "routeUrl": "https://www.google.com/maps/dir/?api=1&origin=45.366833,4.901511&destination=45.3596064,4.9100593&travelmode=driving",
      "lat": 45.3596064,
      "lng": 4.9100593
    },
    {
      "name": "Chèvrerie bellegarde poussieu Cch & cie",
      "theme": "Nature & plein air",
      "themeDetail": "Ferme & animaux",
      "distanceKm": 1.5,
      "durationMin": 8,
      "googleMapsUrl": "https://maps.app.goo.gl/UDvrfFNRsxyKEiZe7",
      "routeUrl": "https://www.google.com/maps/dir/?api=1&origin=45.366833,4.901511&destination=45.3557634,4.9125954&travelmode=driving",
      "lat": 45.3557634,
      "lng": 4.9125954
    },
    {
      "name": "Poney club HARLAND",
      "theme": "Nature & plein air",
      "themeDetail": "Nature & plein air",
      "distanceKm": 2.1,
      "durationMin": 9,
      "googleMapsUrl": "https://maps.app.goo.gl/W1vTG5e2mavA1QN19",
      "routeUrl": "https://www.google.com/maps/dir/?api=1&origin=45.366833,4.901511&destination=45.3649179,4.9287769&travelmode=driving",
      "lat": 45.3649179,
      "lng": 4.9287769
    },
    {
      "name": "La Cas'a Dadou",
      "theme": "Restaurants",
      "themeDetail": "Restaurants",
      "distanceKm": 2.2,
      "durationMin": 9,
      "googleMapsUrl": "https://maps.app.goo.gl/Qub31GCzy7f6KZD76",
      "routeUrl": "https://www.google.com/maps/dir/?api=1&origin=45.366833,4.901511&destination=45.3490234,4.8901037&travelmode=driving",
      "lat": 45.3490234,
      "lng": 4.8901037
    },
    {
      "name": "Le Petit Campagnard",
      "theme": "Restaurants",
      "themeDetail": "Restaurants",
      "distanceKm": 2.8,
      "durationMin": 10,
      "googleMapsUrl": "https://maps.app.goo.gl/MSQ9fuyr7qLBBkqG9",
      "routeUrl": "https://www.google.com/maps/dir/?api=1&origin=45.366833,4.901511&destination=45.391043,4.9089016&travelmode=driving",
      "lat": 45.391043,
      "lng": 4.9089016
    },
    {
      "name": "La Ferme du facteur Enchantée",
      "theme": "Nature & plein air",
      "themeDetail": "Ferme & animaux",
      "distanceKm": 3,
      "durationMin": 10,
      "googleMapsUrl": "https://maps.app.goo.gl/CQu4ZGH6abMiaqwe7",
      "routeUrl": "https://www.google.com/maps/dir/?api=1&origin=45.366833,4.901511&destination=45.3920481,4.8872498&travelmode=driving",
      "lat": 45.3920481,
      "lng": 4.8872498
    },
    {
      "name": "LE JARDIN DU BOIS MARQUIS",
      "theme": "Nature & plein air",
      "themeDetail": "Nature & jardins",
      "distanceKm": 3.4,
      "durationMin": 11,
      "googleMapsUrl": "https://maps.app.goo.gl/FcvZPVBy9Cisr38u7",
      "routeUrl": "https://www.google.com/maps/dir/?api=1&origin=45.366833,4.901511&destination=45.3899242,4.8731433&travelmode=driving",
      "lat": 45.3899242,
      "lng": 4.8731433
    },
    {
      "name": "Château de Bresson",
      "theme": "Patrimoine & culture",
      "themeDetail": "Patrimoine & musées",
      "distanceKm": 4.2,
      "durationMin": 12,
      "googleMapsUrl": "https://maps.app.goo.gl/yr6VpXsri2hws4pU6",
      "routeUrl": "https://www.google.com/maps/dir/?api=1&origin=45.366833,4.901511&destination=45.3578128,4.9530884&travelmode=driving",
      "lat": 45.3578128,
      "lng": 4.9530884
    },
  
    {
      "name": "Escape game géant par VGB EVENT",
      "theme": "Escape Games",
      "themeDetail": "Escape game",
      "distanceKm": 7.1,
      "durationMin": 13,
      "googleMapsUrl": "https://maps.app.goo.gl/kQDCBVDX3fAmVKmB8",
      "routeUrl": "https://www.google.com/maps/dir/?api=1&origin=45.366833,4.901511&destination=45.3382062,4.8212159&travelmode=driving",
      "lat": 45.3382062,
      "lng": 4.8212159
    },
  
    {
      "name": "Vienne Ancient Roman Theatre",
      "theme": "Patrimoine & culture",
      "themeDetail": "Patrimoine & musées",
      "distanceKm": 17.9,
      "durationMin": 22,
      "googleMapsUrl": "https://maps.app.goo.gl/XFh6NvyFLFE7unbs8",
      "routeUrl": "https://www.google.com/maps/dir/?api=1&origin=45.366833,4.901511&destination=45.5268463,4.8727293&travelmode=driving",
      "lat": 45.5268463,
      "lng": 4.8727293
    },
    {
        "name": "Saut de Lorette (randonnée chute d'eau)",
        "theme": "Nature & plein air",
        "themeDetail": "Randonnée & nature",
        "distanceKm": 17.5,
        "durationMin": 21,
        "googleMapsUrl": "https://www.google.com/maps/dir/?utis1&origin=45",
        "routeUrl": "https://maps.app.goo.gl/czrhZeacCvMUL7w36",
        "lat": 45.3406362,
        "lng": 4.6810611
      },
      {
        "name": "Palais idéal du Facteur Cheval",
        "theme": "Patrimoine & culture",
        "themeDetail": "Patrimoine & culture",
        "distanceKm": 15.8,
        "durationMin": 20,
        "googleMapsUrl": "https://www.google.com/maps/dir/7mi",
        "routeUrl": "https://maps.app.goo.gl/ahhz8TyM1QSZARFGE",
        "lat": 45.2562733,
        "lng": 5.0285098
      },
      {
        "name": "Etang de Roussillon",
        "theme": "Nature & plein air",
        "themeDetail": "Nature & plans d'eau",
        "distanceKm": 8,
        "durationMin": 15,
        "googleMapsUrl": "https://www.google.com/maps/dir/",
        "routeUrl": "https://www.google.com/maps/dir/",
        "lat": 45.3716575,
        "lng": 4.7989816
      },
      {
        "name": "La ferme des 3 ailes",
        "theme": "Nature & plein air",
        "themeDetail": "Ferme & animaux",
        "distanceKm": 4.2,
        "durationMin": 12,
        "googleMapsUrl": "https://www.google.com/maps/dir/?api=1&origin=45.366833.4.901511&destination=45",
        "routeUrl": "https://maps.app.goo.gl/wazdRr9UFFT4T2x5",
        "lat": 45.3931651,
        "lng": 4.8634192
      },
      {
        "name": "La Casa Dadou",
        "theme": "Restaurants",
        "themeDetail": "Restaurants",
        "distanceKm": 2.2,
        "durationMin": 9,
        "googleMapsUrl": "https://www.google.com/maps/dir/?api=1&origin=45.366833.4.901511&destination-45",
        "routeUrl": "https://maps.app.goo.gl/Out31GC7f6KZ076",
        "lat": 45.3490234,
        "lng": 4.8901037
      },
      {
        "name": "Chèvrerie bellegarde poussieu Ech & circ",
        "theme": "Nature & plein air",
        "themeDetail": "Ferme & ani",
        "distanceKm": 1.5,
        "durationMin": 8,
        "googleMapsUrl": "https://www.google.com/maps/dir/?api=1&origin=45.366833.4.901511&destination=45",
        "routeUrl": "https://maps.app.goo.gl/UDvrfFNAKEjZe7",
        "lat": 45.3557634,
        "lng": 4.9125954
      },
    {
      "name": "Parc zoologique de Saint-Martin-la-Plaine",
      "theme": "Nature & plein air",
      "themeDetail": "Ferme & animaux",
      "distanceKm": 35.2,
      "durationMin": 31,
      "googleMapsUrl": "https://maps.app.goo.gl/SZgnKss2D1uBt5SZ7",
      "routeUrl": "https://www.google.com/maps/dir/?api=1&origin=45.366833,4.901511&destination=45.546078,4.530164&travelmode=driving",
      "lat": 45.546078,
      "lng": 4.530164
    },
  
    {
      "name": "Aquarium of Lyon",
      "theme": "Aquatique & aquarium",
      "themeDetail": "Aquatique & aquarium",
      "distanceKm": 40.2,
      "durationMin": 35,
      "googleMapsUrl": "https://maps.app.goo.gl/zAFW1GXN9BNiTdjR6",
      "routeUrl": "https://www.google.com/maps/dir/?api=1&origin=45.366833,4.901511&destination=45.723,4.815&travelmode=driving",
      "lat": 45.723,
      "lng": 4.815
    },
  
    {
      "name": "Grotte de Choranche",
      "theme": "Patrimoine & culture",
      "themeDetail": "Grottes & géologie",
      "distanceKm": 52.3,
      "durationMin": 44,
      "googleMapsUrl": "https://maps.app.goo.gl/APTyv6CoPYw7VdZj7",
      "routeUrl": "https://www.google.com/maps/dir/?api=1&origin=45.366833,4.901511&destination=45.056043,5.400939&travelmode=driving",
      "lat": 45.056043,
      "lng": 5.400939
    },
  
    {
      "name": "Medieval city of Pérouges",
      "theme": "Patrimoine & culture",
      "themeDetail": "Patrimoine & musées",
      "distanceKm": 63.4,
      "durationMin": 53,
      "googleMapsUrl": "https://maps.app.goo.gl/kBEFoW2qyVDjaEMH8",
      "routeUrl": "https://www.google.com/maps/dir/?api=1&origin=45.366833,4.901511&destination=45.903296,5.178366&travelmode=driving",
      "lat": 45.903296,
      "lng": 5.178366
    },
  
    {
      "name": "Cerdon caves - Prehistoric Amusement Park",
      "theme": "Patrimoine & culture",
      "themeDetail": "Grottes & géologie",
      "distanceKm": 90.8,
      "durationMin": 62,
      "googleMapsUrl": "https://maps.app.goo.gl/omy1bP1FxuJTbPRQ9",
      "routeUrl": "https://www.google.com/maps/dir/?api=1&origin=45.366833,4.901511&destination=46.0851971,5.4561298&travelmode=driving",
      "lat": 46.0851971,
      "lng": 5.4561298
    }
  ]